{
    "title": "Graphics Development with Python",
    "overview": "Graphics development with Python enables developers to create visual content and applications. Python's libraries like Pygame, Tkinter, and Matplotlib make it accessible for creating games, graphical user interfaces, and data visualizations. This course focuses on practical projects to solidify understanding.",
    "courseDetails": "In this course, you will learn the fundamentals of graphics development using Python. You will master various libraries and tools for creating interactive applications and visual representations. Projects will include game development, GUI applications, and data visualizations. Join our Graphics Development course to enhance your skills and create impressive visual content.",
    "certification": "Upon completing this course, you will receive a certificate, qualifying you as a certified Graphics Developer.",
    "Modules": [
        {"id": "0", "name": "Introduction to Graphics Programming"},
        {"id": "1", "name": "Python Basics for Graphics"},
        {"id": "2", "name": "Pygame Fundamentals"},
        {"id": "3", "name": "Creating 2D Games with Pygame"},
        {"id": "4", "name": "Using Tkinter for GUI Applications"},
        {"id": "5", "name": "Introduction to Matplotlib"},
        {"id": "6", "name": "Data Visualization Techniques"},
        {"id": "7", "name": "Advanced Pygame Concepts"},
        {"id": "8", "name": "Project: Build a Simple Game"},
        {"id": "9", "name": "Project: Create a GUI Application"},
        {"id": "10", "name": "Project: Data Visualization Dashboard"},
        {"id": "11", "name": "Final Exam"},
        {"id": "12", "name": "Final Project Presentation"}
    ],
    "Highlight": [
        {"id": "0", "name": "Interactive Game Development"},
        {"id": "1", "name": "Professional GUI Design"},
        {"id": "2", "name": "Data Analysis and Visualization"},
        {"id": "3", "name": "Hands-on Project-Based Learning"},
        {"id": "4", "name": "Industry-Relevant Tools and Techniques"},
        {"id": "5", "name": "Portfolio Development"},
        {"id": "6", "name": "Collaborative Projects"},
        {"id": "7", "name": "Expert Trainers"},
        {"id": "8", "name": "Networking Opportunities"}
    ],
    "softwareTaught": [
        {"id": "0", "name": "Pygame"},
        {"id": "1", "name": "Tkinter"},
        {"id": "2", "name": "Matplotlib"},
        {"id": "3", "name": "Visual Studio Code"},
        {"id": "4", "name": "Anaconda"},
        {"id": "5", "name": "Jupyter Notebook"}
    ],
    "careerOpportunity": [
        {"id": "0", "name": "Graphics Developer"},
        {"id": "1", "name": "Game Developer"},
        {"id": "2", "name": "Data Visualization Specialist"},
        {"id": "3", "name": "UI/UX Designer"},
        {"id": "4", "name": "Research Assistant"},
        {"id": "5", "name": "Software Engineer"}
    ],
    "skillLevel": "Beginners",
    "duration": "4 Months",
    "classPerWeek": "5 Days",
    "total": "36 Classes"
}